Workbook

Sheet Ringkasan
C1: KAP Dwi Haryadi Nugraha & Rekan
C2: Pengujian Pengendalian (ToC) | E2: Indeks KK | F2: B-6E
C3: Klien | E3: Disusun/Tgl
C4: Periode | D4: 31 Desember 2025 | E4: Direview/Tgl
A6: Ringkasan per SCOT
A7: No | B7: SCOT | C7: Sampel | D7: Penyimpangan | E7: Kesimpulan | F7: Akun Terkait
A8: 1 | B8: Penjualan & Piutang | C8: 25 | D8: ='SCOT 1'!E47 | E8: ='SCOT 1'!E48 | F8: Kas dan Setara Kas, Piutang Usaha, Pendapatan
A9: 2 | B9: Pembelian & Utang | C9: 25 | D9: ='SCOT 2'!E47 | E9: ='SCOT 2'!E48 | F9: Uang Muka & Biaya Dibayar Dimuka, Utang Usaha, Beban Usaha
A10: 3 | B10: Produksi & Persediaan | C10: 25 | D10: ='SCOT 3'!E47 | E10: ='SCOT 3'!E48 | F10: Persediaan, Harga Pokok Penjualan
A11: 4 | B11: Penggajian | C11: 25 | D11: ='SCOT 4'!E46 | E11: ='SCOT 4'!E47
A12: 5 | B12: Aset Tetap | C12: 25 | D12: ='SCOT 5'!E46 | E12: ='SCOT 5'!E47 | F12: Aset Tetap
A14: Satu penyimpangan dari 25 sampel berarti kontrol tidak dapat diandalkan; revisi CRA (B-8) akun terkait menjadi substantif penuh.

Sheet SCOT 1
C1: KAP Dwi Haryadi Nugraha & Rekan
C2: Penjualan & Piutang | I2: Indeks KK | J2: B-6E.1
C3: Klien | I3: Disusun/Tgl
C4: Periode | D4: 31 Desember 2025 | I4: Direview/Tgl
A6: Kontrol Kunci
A7: K1 | B7: Pesanan penjualan disetujui sebelum pengiriman
A8: K2 | B8: Surat jalan dicocokkan ke faktur secara otomatis
A9: K3 | B9: Batas kredit pelanggan dikunci di ERP
A11: Walkthrough (WT) SCOT
A12: Telusuri satu transaksi SCOT ini dari awal sampai tercatat di LK; catat titik rawan salah saji (what can go wrong) dan kontrol kunci yang menanganinya.
A13: Langkah | B13: Tanggal | C13: Dokumen | D13: Uraian dan Kontrol yang Diamati | E13: Kesimpulan
A14: 1
A15: 2
A16: 3
A17: 4
A18: 5
A20: Pengujian Pengendalian (25 Sampel)
A21: No | B21: Tanggal | C21: No. Dokumen | D21: Uraian | E21: Nilai | F21: K1 | G21: K2 | H21: K3 | I21: Hasil | J21: Keterangan
A22: 1 | I22: =IF(COUNTA(F22:H22)=0,"",IF(COUNTIF(F22:H22,"X")>0,"Penyimpangan","Sesuai"))
A23: 2 | I23: =IF(COUNTA(F23:H23)=0,"",IF(COUNTIF(F23:H23,"X")>0,"Penyimpangan","Sesuai"))
A24: 3 | I24: =IF(COUNTA(F24:H24)=0,"",IF(COUNTIF(F24:H24,"X")>0,"Penyimpangan","Sesuai"))
A25: 4 | I25: =IF(COUNTA(F25:H25)=0,"",IF(COUNTIF(F25:H25,"X")>0,"Penyimpangan","Sesuai"))
A26: 5 | I26: =IF(COUNTA(F26:H26)=0,"",IF(COUNTIF(F26:H26,"X")>0,"Penyimpangan","Sesuai"))
A27: 6 | I27: =IF(COUNTA(F27:H27)=0,"",IF(COUNTIF(F27:H27,"X")>0,"Penyimpangan","Sesuai"))
A28: 7 | I28: =IF(COUNTA(F28:H28)=0,"",IF(COUNTIF(F28:H28,"X")>0,"Penyimpangan","Sesuai"))
A29: 8 | I29: =IF(COUNTA(F29:H29)=0,"",IF(COUNTIF(F29:H29,"X")>0,"Penyimpangan","Sesuai"))
A30: 9 | I30: =IF(COUNTA(F30:H30)=0,"",IF(COUNTIF(F30:H30,"X")>0,"Penyimpangan","Sesuai"))
A31: 10 | I31: =IF(COUNTA(F31:H31)=0,"",IF(COUNTIF(F31:H31,"X")>0,"Penyimpangan","Sesuai"))
A32: 11 | I32: =IF(COUNTA(F32:H32)=0,"",IF(COUNTIF(F32:H32,"X")>0,"Penyimpangan","Sesuai"))
A33: 12 | I33: =IF(COUNTA(F33:H33)=0,"",IF(COUNTIF(F33:H33,"X")>0,"Penyimpangan","Sesuai"))
... A46: 25 | I46: =IF(COUNTA(F46:H46)=0,"",IF(COUNTIF(F46:H46,"X")>0,"Penyimpangan","Sesuai"))
D47: Jumlah penyimpangan | E47: =COUNTIF(I22:I46,"Penyimpangan")
D48: Kesimpulan | E48: =IF(COUNTA(I22:I46)-COUNTBLANK(I22:I46)=0,"Belum diuji",IF(E47=0,"Efektif, dapat diandalkan","Tidak efektif, revisi CRA"))

Sheet SCOT 2
C1: KAP Dwi Haryadi Nugraha & Rekan
C2: Pembelian & Utang | I2: Indeks KK | J2: B-6E.2
C3: Klien | I3: Disusun/Tgl
C4: Periode | D4: 31 Desember 2025 | I4: Direview/Tgl
A6: Kontrol Kunci
A7: K1 | B7: Pembelian di atas limit butuh persetujuan berjenjang
A8: K2 | B8: 3-way match PO, penerimaan, tagihan
A9: K3 | B9: Perubahan data pemasok direview
A11: Walkthrough (WT) SCOT
A12: Telusuri satu transaksi SCOT ini dari awal sampai tercatat di LK; catat titik rawan salah saji (what can go wrong) dan kontrol kunci yang menanganinya.
A13: Langkah | B13: Tanggal | C13: Dokumen | D13: Uraian dan Kontrol yang Diamati | E13: Kesimpulan
A14: 1
A15: 2
A16: 3
A17: 4
A18: 5
A20: Pengujian Pengendalian (25 Sampel)
A21: No | B21: Tanggal | C21: No. Dokumen | D21: Uraian | E21: Nilai | F21: K1 | G21: K2 | H21: K3 | I21: Hasil | J21: Keterangan
A22: 1 | I22: =IF(COUNTA(F22:H22)=0,"",IF(COUNTIF(F22:H22,"X")>0,"Penyimpangan","Sesuai"))
A23: 2 | I23: =IF(COUNTA(F23:H23)=0,"",IF(COUNTIF(F23:H23,"X")>0,"Penyimpangan","Sesuai"))
A24: 3 | I24: =IF(COUNTA(F24:H24)=0,"",IF(COUNTIF(F24:H24,"X")>0,"Penyimpangan","Sesuai"))
A25: 4 | I25: =IF(COUNTA(F25:H25)=0,"",IF(COUNTIF(F25:H25,"X")>0,"Penyimpangan","Sesuai"))
A26: 5 | I26: =IF(COUNTA(F26:H26)=0,"",IF(COUNTIF(F26:H26,"X")>0,"Penyimpangan","Sesuai"))
A27: 6 | I27: =IF(COUNTA(F27:H27)=0,"",IF(COUNTIF(F27:H27,"X")>0,"Penyimpangan","Sesuai"))
A28: 7 | I28: =IF(COUNTA(F28:H28)=0,"",IF(COUNTIF(F28:H28,"X")>0,"Penyimpangan","Sesuai"))
A29: 8 | I29: =IF(COUNTA(F29:H29)=0,"",IF(COUNTIF(F29:H29,"X")>0,"Penyimpangan","Sesuai"))
A30: 9 | I30: =IF(COUNTA(F30:H30)=0,"",IF(COUNTIF(F30:H30,"X")>0,"Penyimpangan","Sesuai"))
A31: 10 | I31: =IF(COUNTA(F31:H31)=0,"",IF(COUNTIF(F31:H31,"X")>0,"Penyimpangan","Sesuai"))
A32: 11 | I32: =IF(COUNTA(F32:H32)=0,"",IF(COUNTIF(F32:H32,"X")>0,"Penyimpangan","Sesuai"))
A33: 12 | I33: =IF(COUNTA(F33:H33)=0,"",IF(COUNTIF(F33:H33,"X")>0,"Penyimpangan","Sesuai"))
... A46: 25 | I46: =IF(COUNTA(F46:H46)=0,"",IF(COUNTIF(F46:H46,"X")>0,"Penyimpangan","Sesuai"))
D47: Jumlah penyimpangan | E47: =COUNTIF(I22:I46,"Penyimpangan")
D48: Kesimpulan | E48: =IF(COUNTA(I22:I46)-COUNTBLANK(I22:I46)=0,"Belum diuji",IF(E47=0,"Efektif, dapat diandalkan","Tidak efektif, revisi CRA"))

Sheet SCOT 3
C1: KAP Dwi Haryadi Nugraha & Rekan
C2: Produksi & Persediaan | I2: Indeks KK | J2: B-6E.3
C3: Klien | I3: Disusun/Tgl
C4: Periode | D4: 31 Desember 2025 | I4: Direview/Tgl
A6: Kontrol Kunci
A7: K1 | B7: Stock opname bulanan direkonsiliasi ke ERP
A8: K2 | B8: Standard cost diperbarui per kuartal
A9: K3 | B9: Pengeluaran bahan baku memakai bon resmi
A11: Walkthrough (WT) SCOT
A12: Telusuri satu transaksi SCOT ini dari awal sampai tercatat di LK; catat titik rawan salah saji (what can go wrong) dan kontrol kunci yang menanganinya.
A13: Langkah | B13: Tanggal | C13: Dokumen | D13: Uraian dan Kontrol yang Diamati | E13: Kesimpulan
A14: 1
A15: 2
A16: 3
A17: 4
A18: 5
A20: Pengujian Pengendalian (25 Sampel)
A21: No | B21: Tanggal | C21: No. Dokumen | D21: Uraian | E21: Nilai | F21: K1 | G21: K2 | H21: K3 | I21: Hasil | J21: Keterangan
A22: 1 | I22: =IF(COUNTA(F22:H22)=0,"",IF(COUNTIF(F22:H22,"X")>0,"Penyimpangan","Sesuai"))
A23: 2 | I23: =IF(COUNTA(F23:H23)=0,"",IF(COUNTIF(F23:H23,"X")>0,"Penyimpangan","Sesuai"))
A24: 3 | I24: =IF(COUNTA(F24:H24)=0,"",IF(COUNTIF(F24:H24,"X")>0,"Penyimpangan","Sesuai"))
A25: 4 | I25: =IF(COUNTA(F25:H25)=0,"",IF(COUNTIF(F25:H25,"X")>0,"Penyimpangan","Sesuai"))
A26: 5 | I26: =IF(COUNTA(F26:H26)=0,"",IF(COUNTIF(F26:H26,"X")>0,"Penyimpangan","Sesuai"))
A27: 6 | I27: =IF(COUNTA(F27:H27)=0,"",IF(COUNTIF(F27:H27,"X")>0,"Penyimpangan","Sesuai"))
A28: 7 | I28: =IF(COUNTA(F28:H28)=0,"",IF(COUNTIF(F28:H28,"X")>0,"Penyimpangan","Sesuai"))
A29: 8 | I29: =IF(COUNTA(F29:H29)=0,"",IF(COUNTIF(F29:H29,"X")>0,"Penyimpangan","Sesuai"))
A30: 9 | I30: =IF(COUNTA(F30:H30)=0,"",IF(COUNTIF(F30:H30,"X")>0,"Penyimpangan","Sesuai"))
A31: 10 | I31: =IF(COUNTA(F31:H31)=0,"",IF(COUNTIF(F31:H31,"X")>0,"Penyimpangan","Sesuai"))
A32: 11 | I32: =IF(COUNTA(F32:H32)=0,"",IF(COUNTIF(F32:H32,"X")>0,"Penyimpangan","Sesuai"))
A33: 12 | I33: =IF(COUNTA(F33:H33)=0,"",IF(COUNTIF(F33:H33,"X")>0,"Penyimpangan","Sesuai"))
... A46: 25 | I46: =IF(COUNTA(F46:H46)=0,"",IF(COUNTIF(F46:H46,"X")>0,"Penyimpangan","Sesuai"))
D47: Jumlah penyimpangan | E47: =COUNTIF(I22:I46,"Penyimpangan")
D48: Kesimpulan | E48: =IF(COUNTA(I22:I46)-COUNTBLANK(I22:I46)=0,"Belum diuji",IF(E47=0,"Efektif, dapat diandalkan","Tidak efektif, revisi CRA"))

Sheet SCOT 4
C1: KAP Dwi Haryadi Nugraha & Rekan
C2: Penggajian | H2: Indeks KK | I2: B-6E.4
C3: Klien | H3: Disusun/Tgl
C4: Periode | D4: 31 Desember 2025 | H4: Direview/Tgl
A6: Kontrol Kunci
A7: K1 | B7: Data karyawan baru disetujui HRD
A8: K2 | B8: Rekap absensi direview sebelum payroll
A10: Walkthrough (WT) SCOT
A11: Telusuri satu transaksi SCOT ini dari awal sampai tercatat di LK; catat titik rawan salah saji (what can go wrong) dan kontrol kunci yang menanganinya.
A12: Langkah | B12: Tanggal | C12: Dokumen | D12: Uraian dan Kontrol yang Diamati | E12: Kesimpulan
A13: 1
A14: 2
A15: 3
A16: 4
A17: 5
A19: Pengujian Pengendalian (25 Sampel)
A20: No | B20: Tanggal | C20: No. Dokumen | D20: Uraian | E20: Nilai | F20: K1 | G20: K2 | H20: Hasil | I20: Keterangan
A21: 1 | H21: =IF(COUNTA(F21:G21)=0,"",IF(COUNTIF(F21:G21,"X")>0,"Penyimpangan","Sesuai"))
A22: 2 | H22: =IF(COUNTA(F22:G22)=0,"",IF(COUNTIF(F22:G22,"X")>0,"Penyimpangan","Sesuai"))
A23: 3 | H23: =IF(COUNTA(F23:G23)=0,"",IF(COUNTIF(F23:G23,"X")>0,"Penyimpangan","Sesuai"))
A24: 4 | H24: =IF(COUNTA(F24:G24)=0,"",IF(COUNTIF(F24:G24,"X")>0,"Penyimpangan","Sesuai"))
A25: 5 | H25: =IF(COUNTA(F25:G25)=0,"",IF(COUNTIF(F25:G25,"X")>0,"Penyimpangan","Sesuai"))
A26: 6 | H26: =IF(COUNTA(F26:G26)=0,"",IF(COUNTIF(F26:G26,"X")>0,"Penyimpangan","Sesuai"))
A27: 7 | H27: =IF(COUNTA(F27:G27)=0,"",IF(COUNTIF(F27:G27,"X")>0,"Penyimpangan","Sesuai"))
A28: 8 | H28: =IF(COUNTA(F28:G28)=0,"",IF(COUNTIF(F28:G28,"X")>0,"Penyimpangan","Sesuai"))
A29: 9 | H29: =IF(COUNTA(F29:G29)=0,"",IF(COUNTIF(F29:G29,"X")>0,"Penyimpangan","Sesuai"))
A30: 10 | H30: =IF(COUNTA(F30:G30)=0,"",IF(COUNTIF(F30:G30,"X")>0,"Penyimpangan","Sesuai"))
A31: 11 | H31: =IF(COUNTA(F31:G31)=0,"",IF(COUNTIF(F31:G31,"X")>0,"Penyimpangan","Sesuai"))
A32: 12 | H32: =IF(COUNTA(F32:G32)=0,"",IF(COUNTIF(F32:G32,"X")>0,"Penyimpangan","Sesuai"))
... A45: 25 | H45: =IF(COUNTA(F45:G45)=0,"",IF(COUNTIF(F45:G45,"X")>0,"Penyimpangan","Sesuai"))
D46: Jumlah penyimpangan | E46: =COUNTIF(H21:H45,"Penyimpangan")
D47: Kesimpulan | E47: =IF(COUNTA(H21:H45)-COUNTBLANK(H21:H45)=0,"Belum diuji",IF(E46=0,"Efektif, dapat diandalkan","Tidak efektif, revisi CRA"))

Sheet SCOT 5
C1: KAP Dwi Haryadi Nugraha & Rekan
C2: Aset Tetap | H2: Indeks KK | I2: B-6E.5
C3: Klien | H3: Disusun/Tgl
C4: Periode | D4: 31 Desember 2025 | H4: Direview/Tgl
A6: Kontrol Kunci
A7: K1 | B7: Penambahan aset disetujui sesuai anggaran capex
A8: K2 | B8: Register aset direkonsiliasi ke GL
A10: Walkthrough (WT) SCOT
A11: Telusuri satu transaksi SCOT ini dari awal sampai tercatat di LK; catat titik rawan salah saji (what can go wrong) dan kontrol kunci yang menanganinya.
A12: Langkah | B12: Tanggal | C12: Dokumen | D12: Uraian dan Kontrol yang Diamati | E12: Kesimpulan
A13: 1
A14: 2
A15: 3
A16: 4
A17: 5
A19: Pengujian Pengendalian (25 Sampel)
A20: No | B20: Tanggal | C20: No. Dokumen | D20: Uraian | E20: Nilai | F20: K1 | G20: K2 | H20: Hasil | I20: Keterangan
A21: 1 | H21: =IF(COUNTA(F21:G21)=0,"",IF(COUNTIF(F21:G21,"X")>0,"Penyimpangan","Sesuai"))
A22: 2 | H22: =IF(COUNTA(F22:G22)=0,"",IF(COUNTIF(F22:G22,"X")>0,"Penyimpangan","Sesuai"))
A23: 3 | H23: =IF(COUNTA(F23:G23)=0,"",IF(COUNTIF(F23:G23,"X")>0,"Penyimpangan","Sesuai"))
A24: 4 | H24: =IF(COUNTA(F24:G24)=0,"",IF(COUNTIF(F24:G24,"X")>0,"Penyimpangan","Sesuai"))
A25: 5 | H25: =IF(COUNTA(F25:G25)=0,"",IF(COUNTIF(F25:G25,"X")>0,"Penyimpangan","Sesuai"))
A26: 6 | H26: =IF(COUNTA(F26:G26)=0,"",IF(COUNTIF(F26:G26,"X")>0,"Penyimpangan","Sesuai"))
A27: 7 | H27: =IF(COUNTA(F27:G27)=0,"",IF(COUNTIF(F27:G27,"X")>0,"Penyimpangan","Sesuai"))
A28: 8 | H28: =IF(COUNTA(F28:G28)=0,"",IF(COUNTIF(F28:G28,"X")>0,"Penyimpangan","Sesuai"))
A29: 9 | H29: =IF(COUNTA(F29:G29)=0,"",IF(COUNTIF(F29:G29,"X")>0,"Penyimpangan","Sesuai"))
A30: 10 | H30: =IF(COUNTA(F30:G30)=0,"",IF(COUNTIF(F30:G30,"X")>0,"Penyimpangan","Sesuai"))
A31: 11 | H31: =IF(COUNTA(F31:G31)=0,"",IF(COUNTIF(F31:G31,"X")>0,"Penyimpangan","Sesuai"))
A32: 12 | H32: =IF(COUNTA(F32:G32)=0,"",IF(COUNTIF(F32:G32,"X")>0,"Penyimpangan","Sesuai"))
... A45: 25 | H45: =IF(COUNTA(F45:G45)=0,"",IF(COUNTIF(F45:G45,"X")>0,"Penyimpangan","Sesuai"))
D46: Jumlah penyimpangan | E46: =COUNTIF(H21:H45,"Penyimpangan")
D47: Kesimpulan | E47: =IF(COUNTA(H21:H45)-COUNTBLANK(H21:H45)=0,"Belum diuji",IF(E46=0,"Efektif, dapat diandalkan","Tidak efektif, revisi CRA"))
